[{"id":25,"songId":1,"img":"https://robohash.org/temporaprovidentconsequatur.png?size=50x50&set=set1","titulo":"aliquam augue","precio":69,"descripcion":"quisque porta volutpat erat quisque erat eros viverra eget congue eget semper rutrum nulla","nombre":"Decca","apellido":"Delacoste"},
{"id":43,"songId":2,"img":"https://robohash.org/facerereiciendisiste.png?size=50x50&set=set1","titulo":"eget congue eget","precio":37,"descripcion":"fermentum justo nec condimentum neque sapien placerat ante nulla justo aliquam quis turpis eget elit","nombre":"Ezekiel","apellido":"Brachell"},
{"id":13,"songId":3,"img":"https://robohash.org/rationeperspiciatisdolore.png?size=50x50&set=set1","titulo":"congue elementum","precio":34,"descripcion":"porttitor lorem id ligula suspendisse ornare consequat lectus in est risus auctor","nombre":"Cherin","apellido":"Pay"},
{"id":17,"songId":4,"img":"https://robohash.org/fugaerrorpariatur.png?size=50x50&set=set1","titulo":"pellentesque quisque","precio":19,"descripcion":"eget nunc donec quis orci eget orci vehicula condimentum curabitur in","nombre":"Gifford","apellido":"Tarr"},
{"id":22,"songId":5,"img":"https://robohash.org/remnesciuntconsequatur.png?size=50x50&set=set1","titulo":"cubilia curae","precio":63,"descripcion":"ac leo pellentesque ultrices mattis odio donec vitae nisi nam ultrices libero non mattis pulvinar","nombre":"Kassie","apellido":"Durrance"},
{"id":20,"songId":6,"img":"https://robohash.org/illumcumqueatque.png?size=50x50&set=set1","titulo":"id nulla ultrices","precio":95,"descripcion":"ante ipsum primis in faucibus orci luctus et ultrices posuere cubilia","nombre":"Amye","apellido":"Tregona"},
{"id":15,"songId":7,"img":"https://robohash.org/numquamadearum.png?size=50x50&set=set1","titulo":"justo aliquam","precio":24,"descripcion":"accumsan tortor quis turpis sed ante vivamus tortor duis mattis egestas metus aenean fermentum donec","nombre":"Stesha","apellido":"Mcettrick"},
{"id":22,"songId":8,"img":"https://robohash.org/eteaquasi.png?size=50x50&set=set1","titulo":"curae mauris","precio":24,"descripcion":"nam ultrices libero non mattis pulvinar nulla pede ullamcorper augue a suscipit","nombre":"Hope","apellido":"Eastes"},
{"id":24,"songId":9,"img":"https://robohash.org/etsuscipithic.png?size=50x50&set=set1","titulo":"morbi sem mauris","precio":13,"descripcion":"in blandit ultrices enim lorem ipsum dolor sit amet consectetuer adipiscing elit proin interdum","nombre":"Bertrand","apellido":"Bernardoux"},
{"id":26,"songId":10,"img":"https://robohash.org/enimhicut.png?size=50x50&set=set1","titulo":"vitae quam suspendisse","precio":83,"descripcion":"lorem id ligula suspendisse ornare consequat lectus in est risus","nombre":"Tandy","apellido":"Ablett"},
{"id":42,"songId":11,"img":"https://robohash.org/etnesciuntsit.png?size=50x50&set=set1","titulo":"semper","precio":15,"descripcion":"odio justo sollicitudin ut suscipit a feugiat et eros vestibulum ac est lacinia nisi","nombre":"Barr","apellido":"Delgaty"},
{"id":8,"songId":12,"img":"https://robohash.org/estrepellatnecessitatibus.png?size=50x50&set=set1","titulo":"nisl ut","precio":64,"descripcion":"tortor risus dapibus augue vel accumsan tellus nisi eu orci mauris lacinia sapien quis","nombre":"Annabel","apellido":"Senten"},
{"id":8,"songId":13,"img":"https://robohash.org/culpaincidunteum.png?size=50x50&set=set1","titulo":"pellentesque at","precio":74,"descripcion":"donec odio justo sollicitudin ut suscipit a feugiat et eros","nombre":"Nikolaus","apellido":"Rodge"},
{"id":32,"songId":14,"img":"https://robohash.org/suntmodiquibusdam.png?size=50x50&set=set1","titulo":"nam dui","precio":56,"descripcion":"morbi porttitor lorem id ligula suspendisse ornare consequat lectus in est risus auctor sed tristique","nombre":"Doro","apellido":"Abbey"},
{"id":28,"songId":15,"img":"https://robohash.org/assumendaaliasqui.png?size=50x50&set=set1","titulo":"luctus et ultrices","precio":53,"descripcion":"sagittis sapien cum sociis natoque penatibus et magnis dis parturient","nombre":"Radcliffe","apellido":"Yeabsley"},
{"id":7,"songId":16,"img":"https://robohash.org/repudiandaevitaefugiat.png?size=50x50&set=set1","titulo":"nunc donec","precio":29,"descripcion":"aliquam augue quam sollicitudin vitae consectetuer eget rutrum at lorem integer tincidunt ante vel ipsum","nombre":"Delainey","apellido":"Belf"},
{"id":13,"songId":17,"img":"https://robohash.org/doloribusdolorducimus.png?size=50x50&set=set1","titulo":"diam cras","precio":21,"descripcion":"et ultrices posuere cubilia curae donec pharetra magna vestibulum aliquet ultrices erat tortor","nombre":"Skell","apellido":"Elderidge"},
{"id":18,"songId":18,"img":"https://robohash.org/abquodrerum.png?size=50x50&set=set1","titulo":"ac enim in","precio":58,"descripcion":"molestie lorem quisque ut erat curabitur gravida nisi at nibh","nombre":"Sandye","apellido":"Fearns"},
{"id":12,"songId":19,"img":"https://robohash.org/estofficiisvero.png?size=50x50&set=set1","titulo":"morbi","precio":79,"descripcion":"ut nunc vestibulum ante ipsum primis in faucibus orci luctus et ultrices","nombre":"Margalo","apellido":"McBrearty"},
{"id":19,"songId":20,"img":"https://robohash.org/quodrerumamet.png?size=50x50&set=set1","titulo":"nascetur","precio":100,"descripcion":"pulvinar lobortis est phasellus sit amet erat nulla tempus vivamus in","nombre":"Fania","apellido":"Gotfrey"},
{"id":45,"songId":21,"img":"https://robohash.org/modidoloresautem.png?size=50x50&set=set1","titulo":"habitasse platea dictumst","precio":72,"descripcion":"ac est lacinia nisi venenatis tristique fusce congue diam id ornare imperdiet sapien urna pretium","nombre":"Ardella","apellido":"Warre"},
{"id":35,"songId":22,"img":"https://robohash.org/etinventoreomnis.png?size=50x50&set=set1","titulo":"quis lectus","precio":84,"descripcion":"quam turpis adipiscing lorem vitae mattis nibh ligula nec sem duis","nombre":"Corene","apellido":"Dake"},
{"id":46,"songId":23,"img":"https://robohash.org/liberoillumdolorem.png?size=50x50&set=set1","titulo":"at nulla","precio":98,"descripcion":"molestie hendrerit at vulputate vitae nisl aenean lectus pellentesque eget nunc donec quis orci","nombre":"Leeland","apellido":"Dimitru"},
{"id":29,"songId":24,"img":"https://robohash.org/laboriosamvoluptatemaliquam.png?size=50x50&set=set1","titulo":"adipiscing lorem","precio":57,"descripcion":"tristique in tempus sit amet sem fusce consequat nulla nisl","nombre":"Edwina","apellido":"Haswell"},
{"id":21,"songId":25,"img":"https://robohash.org/estconsequaturaut.png?size=50x50&set=set1","titulo":"sed","precio":64,"descripcion":"donec vitae nisi nam ultrices libero non mattis pulvinar nulla","nombre":"Olympia","apellido":"Nestle"},
{"id":14,"songId":26,"img":"https://robohash.org/oditeumest.png?size=50x50&set=set1","titulo":"massa tempor convallis","precio":54,"descripcion":"accumsan felis ut at dolor quis odio consequat varius integer ac leo","nombre":"Jacky","apellido":"Berka"},
{"id":1,"songId":27,"img":"https://robohash.org/voluptatemaliasdolor.png?size=50x50&set=set1","titulo":"lectus pellentesque","precio":29,"descripcion":"enim blandit mi in porttitor pede justo eu massa donec dapibus duis at velit eu","nombre":"Hodge","apellido":"Burberry"},
{"id":10,"songId":28,"img":"https://robohash.org/eosadipisciexercitationem.png?size=50x50&set=set1","titulo":"convallis nunc","precio":76,"descripcion":"vulputate luctus cum sociis natoque penatibus et magnis dis parturient montes nascetur ridiculus mus vivamus","nombre":"Tybi","apellido":"Lexa"},
{"id":44,"songId":29,"img":"https://robohash.org/istedoloremomnis.png?size=50x50&set=set1","titulo":"justo eu massa","precio":45,"descripcion":"vel sem sed sagittis nam congue risus semper porta volutpat quam","nombre":"Spike","apellido":"Pargiter"},
{"id":37,"songId":30,"img":"https://robohash.org/dictaestut.png?size=50x50&set=set1","titulo":"sed","precio":81,"descripcion":"ornare imperdiet sapien urna pretium nisl ut volutpat sapien arcu","nombre":"Willetta","apellido":"Innott"},
{"id":44,"songId":31,"img":"https://robohash.org/delectusabest.png?size=50x50&set=set1","titulo":"nunc purus phasellus","precio":5,"descripcion":"amet diam in magna bibendum imperdiet nullam orci pede venenatis non sodales sed tincidunt","nombre":"Kin","apellido":"Shergill"},
{"id":50,"songId":32,"img":"https://robohash.org/abinaut.png?size=50x50&set=set1","titulo":"justo sollicitudin ut","precio":39,"descripcion":"vivamus metus arcu adipiscing molestie hendrerit at vulputate vitae nisl aenean","nombre":"Samson","apellido":"Aust"},
{"id":25,"songId":33,"img":"https://robohash.org/odiovoluptatemperspiciatis.png?size=50x50&set=set1","titulo":"donec ut mauris","precio":75,"descripcion":"sed vel enim sit amet nunc viverra dapibus nulla suscipit ligula in lacus","nombre":"Man","apellido":"Pudsall"},
{"id":37,"songId":34,"img":"https://robohash.org/doloribusnecessitatibusnulla.png?size=50x50&set=set1","titulo":"nulla tellus","precio":28,"descripcion":"dolor vel est donec odio justo sollicitudin ut suscipit a","nombre":"Zola","apellido":"Gawkes"},
{"id":8,"songId":35,"img":"https://robohash.org/quihicexplicabo.png?size=50x50&set=set1","titulo":"mi pede","precio":53,"descripcion":"nunc nisl duis bibendum felis sed interdum venenatis turpis enim blandit","nombre":"Pansie","apellido":"Devote"},
{"id":3,"songId":36,"img":"https://robohash.org/eosporrofuga.png?size=50x50&set=set1","titulo":"quis turpis eget","precio":29,"descripcion":"dui proin leo odio porttitor id consequat in consequat ut nulla sed accumsan","nombre":"Arielle","apellido":"Goudie"},
{"id":14,"songId":37,"img":"https://robohash.org/quaeratabesse.png?size=50x50&set=set1","titulo":"dui maecenas tristique","precio":25,"descripcion":"viverra diam vitae quam suspendisse potenti nullam porttitor lacus at turpis donec posuere metus vitae","nombre":"Nydia","apellido":"Jowers"},
{"id":25,"songId":38,"img":"https://robohash.org/velquibusdamvoluptas.png?size=50x50&set=set1","titulo":"quis tortor id","precio":9,"descripcion":"aliquam lacus morbi quis tortor id nulla ultrices aliquet maecenas leo odio condimentum id","nombre":"Israel","apellido":"Caudray"},
{"id":31,"songId":39,"img":"https://robohash.org/suntmaximeconsequatur.png?size=50x50&set=set1","titulo":"magna","precio":28,"descripcion":"quam a odio in hac habitasse platea dictumst maecenas ut","nombre":"Gunter","apellido":"Harbidge"},
{"id":36,"songId":40,"img":"https://robohash.org/quodsitet.png?size=50x50&set=set1","titulo":"vitae","precio":30,"descripcion":"vestibulum ac est lacinia nisi venenatis tristique fusce congue diam id ornare imperdiet sapien","nombre":"Berenice","apellido":"Hatcliffe"},
{"id":1,"songId":41,"img":"https://robohash.org/etnonmagnam.png?size=50x50&set=set1","titulo":"pretium","precio":64,"descripcion":"donec ut dolor morbi vel lectus in quam fringilla rhoncus mauris enim leo","nombre":"Florinda","apellido":"Sydenham"},
{"id":29,"songId":42,"img":"https://robohash.org/exdoloresest.png?size=50x50&set=set1","titulo":"dictumst aliquam","precio":3,"descripcion":"urna pretium nisl ut volutpat sapien arcu sed augue aliquam erat volutpat in congue etiam","nombre":"Jermaine","apellido":"Blew"},
{"id":17,"songId":43,"img":"https://robohash.org/quisquaminciduntest.png?size=50x50&set=set1","titulo":"aenean lectus","precio":84,"descripcion":"elementum eu interdum eu tincidunt in leo maecenas pulvinar lobortis est phasellus sit","nombre":"Lothaire","apellido":"Fruin"},
{"id":30,"songId":44,"img":"https://robohash.org/remexplicaboaut.png?size=50x50&set=set1","titulo":"nisi venenatis","precio":33,"descripcion":"ut tellus nulla ut erat id mauris vulputate elementum nullam varius nulla facilisi cras","nombre":"Marci","apellido":"Chatell"},
{"id":47,"songId":45,"img":"https://robohash.org/atquevelconsectetur.png?size=50x50&set=set1","titulo":"vestibulum","precio":24,"descripcion":"vulputate nonummy maecenas tincidunt lacus at velit vivamus vel nulla eget eros elementum pellentesque quisque","nombre":"Conney","apellido":"De Minico"},
{"id":21,"songId":46,"img":"https://robohash.org/laudantiumdolorevoluptatem.png?size=50x50&set=set1","titulo":"lectus pellentesque at","precio":11,"descripcion":"tempor convallis nulla neque libero convallis eget eleifend luctus ultricies eu nibh quisque id justo","nombre":"Wait","apellido":"Burditt"},
{"id":9,"songId":47,"img":"https://robohash.org/magnamfacilisea.png?size=50x50&set=set1","titulo":"odio curabitur","precio":37,"descripcion":"tincidunt nulla mollis molestie lorem quisque ut erat curabitur gravida nisi at nibh in hac","nombre":"Maxie","apellido":"Birkin"},
{"id":35,"songId":48,"img":"https://robohash.org/ducimustemporatemporibus.png?size=50x50&set=set1","titulo":"velit","precio":73,"descripcion":"vel augue vestibulum rutrum rutrum neque aenean auctor gravida sem praesent","nombre":"Kayla","apellido":"Haws"},
{"id":4,"songId":49,"img":"https://robohash.org/nesciuntdolorumquo.png?size=50x50&set=set1","titulo":"erat vestibulum sed","precio":59,"descripcion":"fermentum justo nec condimentum neque sapien placerat ante nulla justo aliquam quis","nombre":"Reginald","apellido":"Fearney"},
{"id":15,"songId":50,"img":"https://robohash.org/maioresipsamdeleniti.png?size=50x50&set=set1","titulo":"lacus morbi quis","precio":30,"descripcion":"non quam nec dui luctus rutrum nulla tellus in sagittis dui","nombre":"Retha","apellido":"Hambelton"},
{"id":44,"songId":51,"img":"https://robohash.org/quivelitlaudantium.png?size=50x50&set=set1","titulo":"ridiculus mus vivamus","precio":32,"descripcion":"eleifend quam a odio in hac habitasse platea dictumst maecenas ut massa quis","nombre":"Jacquetta","apellido":"Dillet"},
{"id":1,"songId":52,"img":"https://robohash.org/dignissimossedrepudiandae.png?size=50x50&set=set1","titulo":"aliquam","precio":22,"descripcion":"erat quisque erat eros viverra eget congue eget semper rutrum","nombre":"Ronnie","apellido":"Love"},
{"id":31,"songId":53,"img":"https://robohash.org/quorerumet.png?size=50x50&set=set1","titulo":"nec","precio":25,"descripcion":"eu tincidunt in leo maecenas pulvinar lobortis est phasellus sit amet erat nulla tempus","nombre":"Kyla","apellido":"Perks"},
{"id":15,"songId":54,"img":"https://robohash.org/nobisaperiamdolores.png?size=50x50&set=set1","titulo":"turpis donec","precio":63,"descripcion":"nulla nunc purus phasellus in felis donec semper sapien a libero","nombre":"Anthia","apellido":"Tabbernor"},
{"id":21,"songId":55,"img":"https://robohash.org/quamrerumquasi.png?size=50x50&set=set1","titulo":"hac habitasse","precio":70,"descripcion":"maecenas tristique est et tempus semper est quam pharetra magna ac consequat metus sapien ut","nombre":"Alfonse","apellido":"Shand"},
{"id":31,"songId":56,"img":"https://robohash.org/etvelitrepellat.png?size=50x50&set=set1","titulo":"leo maecenas pulvinar","precio":15,"descripcion":"elementum nullam varius nulla facilisi cras non velit nec nisi vulputate nonummy maecenas","nombre":"Erastus","apellido":"Roskell"},
{"id":31,"songId":57,"img":"https://robohash.org/doloribusevenietalias.png?size=50x50&set=set1","titulo":"donec semper sapien","precio":2,"descripcion":"duis consequat dui nec nisi volutpat eleifend donec ut dolor morbi vel lectus in","nombre":"Humphrey","apellido":"Mantripp"},
{"id":14,"songId":58,"img":"https://robohash.org/ainventoreut.png?size=50x50&set=set1","titulo":"gravida nisi","precio":81,"descripcion":"cubilia curae donec pharetra magna vestibulum aliquet ultrices erat tortor sollicitudin mi sit amet","nombre":"Cybil","apellido":"Beaten"},
{"id":15,"songId":59,"img":"https://robohash.org/repudiandaesedmollitia.png?size=50x50&set=set1","titulo":"curae donec","precio":61,"descripcion":"in ante vestibulum ante ipsum primis in faucibus orci luctus et ultrices","nombre":"Alla","apellido":"Pietruszka"},
{"id":50,"songId":60,"img":"https://robohash.org/estmolestiaslaborum.png?size=50x50&set=set1","titulo":"erat tortor sollicitudin","precio":3,"descripcion":"interdum mauris non ligula pellentesque ultrices phasellus id sapien in sapien iaculis congue vivamus","nombre":"Arluene","apellido":"Barde"},
{"id":4,"songId":61,"img":"https://robohash.org/utremaliquid.png?size=50x50&set=set1","titulo":"pretium iaculis diam","precio":66,"descripcion":"sapien sapien non mi integer ac neque duis bibendum morbi","nombre":"Mair","apellido":"Kirman"},
{"id":29,"songId":62,"img":"https://robohash.org/dignissimosdictain.png?size=50x50&set=set1","titulo":"blandit","precio":65,"descripcion":"quis augue luctus tincidunt nulla mollis molestie lorem quisque ut erat curabitur gravida nisi","nombre":"Clotilda","apellido":"Plose"},
{"id":34,"songId":63,"img":"https://robohash.org/minuspariaturdolore.png?size=50x50&set=set1","titulo":"in","precio":43,"descripcion":"cubilia curae duis faucibus accumsan odio curabitur convallis duis consequat dui nec nisi","nombre":"Mayne","apellido":"Kief"},
{"id":13,"songId":64,"img":"https://robohash.org/solutavoluptatemqui.png?size=50x50&set=set1","titulo":"suspendisse","precio":86,"descripcion":"platea dictumst aliquam augue quam sollicitudin vitae consectetuer eget rutrum at lorem integer tincidunt","nombre":"Robin","apellido":"Cinnamond"},
{"id":7,"songId":65,"img":"https://robohash.org/temporibusvitaequos.png?size=50x50&set=set1","titulo":"ut suscipit a","precio":80,"descripcion":"sit amet diam in magna bibendum imperdiet nullam orci pede venenatis non sodales","nombre":"Sergent","apellido":"de Marco"},
{"id":8,"songId":66,"img":"https://robohash.org/consequaturdistinctioeum.png?size=50x50&set=set1","titulo":"volutpat","precio":31,"descripcion":"pellentesque volutpat dui maecenas tristique est et tempus semper est","nombre":"Rosetta","apellido":"Readmire"},
{"id":42,"songId":67,"img":"https://robohash.org/velitutdolores.png?size=50x50&set=set1","titulo":"justo","precio":86,"descripcion":"convallis tortor risus dapibus augue vel accumsan tellus nisi eu orci mauris lacinia sapien quis","nombre":"Richmond","apellido":"Niave"},
{"id":44,"songId":68,"img":"https://robohash.org/sintexpeditaad.png?size=50x50&set=set1","titulo":"ante ipsum","precio":69,"descripcion":"amet cursus id turpis integer aliquet massa id lobortis convallis tortor risus","nombre":"Orion","apellido":"Kenninghan"},
{"id":9,"songId":69,"img":"https://robohash.org/estaspernaturearum.png?size=50x50&set=set1","titulo":"suspendisse potenti","precio":55,"descripcion":"vel accumsan tellus nisi eu orci mauris lacinia sapien quis libero nullam sit amet","nombre":"Amalea","apellido":"Pargiter"},
{"id":12,"songId":70,"img":"https://robohash.org/maximecommodiautem.png?size=50x50&set=set1","titulo":"sociis natoque","precio":68,"descripcion":"accumsan tellus nisi eu orci mauris lacinia sapien quis libero nullam sit","nombre":"Maritsa","apellido":"Burger"},
{"id":1,"songId":71,"img":"https://robohash.org/atquequibusdamquod.png?size=50x50&set=set1","titulo":"consequat varius","precio":78,"descripcion":"blandit non interdum in ante vestibulum ante ipsum primis in faucibus orci luctus","nombre":"Shawnee","apellido":"Habershon"},
{"id":31,"songId":72,"img":"https://robohash.org/evenietquaeratiure.png?size=50x50&set=set1","titulo":"donec diam","precio":89,"descripcion":"sed vestibulum sit amet cursus id turpis integer aliquet massa id lobortis convallis tortor","nombre":"Abdul","apellido":"Illesley"},
{"id":44,"songId":73,"img":"https://robohash.org/voluptasnulladolorum.png?size=50x50&set=set1","titulo":"turpis adipiscing","precio":84,"descripcion":"in faucibus orci luctus et ultrices posuere cubilia curae duis faucibus accumsan odio curabitur","nombre":"Sophia","apellido":"Hannum"},
{"id":15,"songId":74,"img":"https://robohash.org/atsapienteest.png?size=50x50&set=set1","titulo":"dui vel","precio":4,"descripcion":"imperdiet sapien urna pretium nisl ut volutpat sapien arcu sed","nombre":"Leann","apellido":"Whibley"},
{"id":22,"songId":75,"img":"https://robohash.org/etconsequaturin.png?size=50x50&set=set1","titulo":"potenti","precio":64,"descripcion":"nibh in quis justo maecenas rhoncus aliquam lacus morbi quis tortor id nulla ultrices aliquet","nombre":"Rowland","apellido":"Ray"},
{"id":19,"songId":76,"img":"https://robohash.org/eumlaudantiumeum.png?size=50x50&set=set1","titulo":"praesent blandit nam","precio":97,"descripcion":"luctus tincidunt nulla mollis molestie lorem quisque ut erat curabitur gravida nisi","nombre":"Dru","apellido":"Godwyn"},
{"id":39,"songId":77,"img":"https://robohash.org/rationeporroexercitationem.png?size=50x50&set=set1","titulo":"id massa","precio":43,"descripcion":"justo eu massa donec dapibus duis at velit eu est congue elementum in hac habitasse","nombre":"Nora","apellido":"Gowry"},
{"id":50,"songId":78,"img":"https://robohash.org/eumquisquamet.png?size=50x50&set=set1","titulo":"convallis duis consequat","precio":51,"descripcion":"curabitur in libero ut massa volutpat convallis morbi odio odio elementum eu interdum","nombre":"Gauthier","apellido":"Petofi"},
{"id":14,"songId":79,"img":"https://robohash.org/fugaametmagni.png?size=50x50&set=set1","titulo":"tellus nisi","precio":67,"descripcion":"non velit donec diam neque vestibulum eget vulputate ut ultrices vel augue vestibulum","nombre":"Clio","apellido":"Beeching"},
{"id":27,"songId":80,"img":"https://robohash.org/oditnamqui.png?size=50x50&set=set1","titulo":"est congue","precio":72,"descripcion":"arcu libero rutrum ac lobortis vel dapibus at diam nam tristique tortor eu pede","nombre":"Darda","apellido":"Chippin"},
{"id":46,"songId":81,"img":"https://robohash.org/ametevenieteos.png?size=50x50&set=set1","titulo":"eleifend pede","precio":48,"descripcion":"porttitor id consequat in consequat ut nulla sed accumsan felis","nombre":"Rennie","apellido":"Shew"},
{"id":26,"songId":82,"img":"https://robohash.org/estvoluptatemamet.png?size=50x50&set=set1","titulo":"amet consectetuer adipiscing","precio":22,"descripcion":"eu mi nulla ac enim in tempor turpis nec euismod scelerisque quam turpis adipiscing","nombre":"Emmi","apellido":"Gosnoll"},
{"id":20,"songId":83,"img":"https://robohash.org/idetaperiam.png?size=50x50&set=set1","titulo":"condimentum id","precio":55,"descripcion":"aenean lectus pellentesque eget nunc donec quis orci eget orci vehicula condimentum curabitur","nombre":"Bartolemo","apellido":"Wybern"},
{"id":29,"songId":84,"img":"https://robohash.org/ututquibusdam.png?size=50x50&set=set1","titulo":"ac est","precio":91,"descripcion":"consectetuer adipiscing elit proin interdum mauris non ligula pellentesque ultrices phasellus id","nombre":"Stephannie","apellido":"Lumb"},
{"id":9,"songId":85,"img":"https://robohash.org/delenitirerumcorporis.png?size=50x50&set=set1","titulo":"luctus","precio":56,"descripcion":"orci luctus et ultrices posuere cubilia curae mauris viverra diam","nombre":"Georgeta","apellido":"Bockman"},
{"id":34,"songId":86,"img":"https://robohash.org/consequaturenimnon.png?size=50x50&set=set1","titulo":"odio","precio":69,"descripcion":"nisl nunc rhoncus dui vel sem sed sagittis nam congue risus semper porta volutpat","nombre":"Chloette","apellido":"Siddall"},
{"id":29,"songId":87,"img":"https://robohash.org/vellaboriosamut.png?size=50x50&set=set1","titulo":"ultrices vel augue","precio":53,"descripcion":"consectetuer adipiscing elit proin risus praesent lectus vestibulum quam sapien","nombre":"Dougie","apellido":"Harvard"},
{"id":23,"songId":88,"img":"https://robohash.org/delenitieligendicorrupti.png?size=50x50&set=set1","titulo":"proin eu","precio":82,"descripcion":"congue vivamus metus arcu adipiscing molestie hendrerit at vulputate vitae","nombre":"Janeen","apellido":"Sidwick"},
{"id":46,"songId":89,"img":"https://robohash.org/aliquidmollitiamolestias.png?size=50x50&set=set1","titulo":"gravida nisi at","precio":20,"descripcion":"lacus at turpis donec posuere metus vitae ipsum aliquam non mauris","nombre":"Adiana","apellido":"Ascroft"},
{"id":30,"songId":90,"img":"https://robohash.org/isteautemdelectus.png?size=50x50&set=set1","titulo":"ante","precio":48,"descripcion":"in ante vestibulum ante ipsum primis in faucibus orci luctus et ultrices posuere cubilia curae","nombre":"Astrix","apellido":"McQuillin"},
{"id":22,"songId":91,"img":"https://robohash.org/auteligendiqui.png?size=50x50&set=set1","titulo":"felis","precio":75,"descripcion":"lacus morbi quis tortor id nulla ultrices aliquet maecenas leo odio condimentum id luctus nec","nombre":"Eveleen","apellido":"Frensche"},
{"id":2,"songId":92,"img":"https://robohash.org/etfacilismagnam.png?size=50x50&set=set1","titulo":"dolor morbi","precio":86,"descripcion":"natoque penatibus et magnis dis parturient montes nascetur ridiculus mus vivamus vestibulum sagittis sapien","nombre":"Phoebe","apellido":"MacInherney"},
{"id":14,"songId":93,"img":"https://robohash.org/autconsequaturtemporibus.png?size=50x50&set=set1","titulo":"maecenas tristique","precio":81,"descripcion":"quam sollicitudin vitae consectetuer eget rutrum at lorem integer tincidunt ante vel ipsum","nombre":"Cicely","apellido":"Stouther"},
{"id":29,"songId":94,"img":"https://robohash.org/sitquibusdamipsum.png?size=50x50&set=set1","titulo":"sodales scelerisque","precio":82,"descripcion":"ut erat id mauris vulputate elementum nullam varius nulla facilisi cras","nombre":"Portia","apellido":"Barosch"},
{"id":30,"songId":95,"img":"https://robohash.org/nisisintoccaecati.png?size=50x50&set=set1","titulo":"dui","precio":90,"descripcion":"nunc viverra dapibus nulla suscipit ligula in lacus curabitur at ipsum ac","nombre":"Anatole","apellido":"Tardiff"},
{"id":13,"songId":96,"img":"https://robohash.org/harumnumquameius.png?size=50x50&set=set1","titulo":"rutrum","precio":66,"descripcion":"id ornare imperdiet sapien urna pretium nisl ut volutpat sapien arcu sed augue aliquam erat","nombre":"Hedda","apellido":"Flaune"},
{"id":31,"songId":97,"img":"https://robohash.org/sedsedcorrupti.png?size=50x50&set=set1","titulo":"non mauris","precio":79,"descripcion":"donec semper sapien a libero nam dui proin leo odio porttitor","nombre":"Olympie","apellido":"Coan"},
{"id":17,"songId":98,"img":"https://robohash.org/harumiddolores.png?size=50x50&set=set1","titulo":"nec molestie sed","precio":65,"descripcion":"duis consequat dui nec nisi volutpat eleifend donec ut dolor morbi vel","nombre":"Dewain","apellido":"Raggatt"},
{"id":2,"songId":99,"img":"https://robohash.org/odithiceveniet.png?size=50x50&set=set1","titulo":"at","precio":93,"descripcion":"pede justo lacinia eget tincidunt eget tempus vel pede morbi porttitor","nombre":"Corrianne","apellido":"Wyse"},
{"id":23,"songId":100,"img":"https://robohash.org/vitaesuntarchitecto.png?size=50x50&set=set1","titulo":"justo","precio":87,"descripcion":"mi integer ac neque duis bibendum morbi non quam nec dui luctus","nombre":"Dom","apellido":"Kernocke"},
{"id":30,"songId":101,"img":"https://robohash.org/aspernatursapientequia.png?size=50x50&set=set1","titulo":"a feugiat et","precio":31,"descripcion":"nonummy maecenas tincidunt lacus at velit vivamus vel nulla eget eros elementum pellentesque quisque porta","nombre":"Brice","apellido":"Fahy"},
{"id":32,"songId":102,"img":"https://robohash.org/autemhiceveniet.png?size=50x50&set=set1","titulo":"nulla sed","precio":61,"descripcion":"sed tincidunt eu felis fusce posuere felis sed lacus morbi sem","nombre":"Ericha","apellido":"Dufore"},
{"id":4,"songId":103,"img":"https://robohash.org/laboriosamfugitmaiores.png?size=50x50&set=set1","titulo":"faucibus orci luctus","precio":86,"descripcion":"nisl aenean lectus pellentesque eget nunc donec quis orci eget orci","nombre":"Norry","apellido":"Whaplington"},
{"id":23,"songId":104,"img":"https://robohash.org/quisremaspernatur.png?size=50x50&set=set1","titulo":"ac nulla sed","precio":86,"descripcion":"donec diam neque vestibulum eget vulputate ut ultrices vel augue","nombre":"Jan","apellido":"Gimlet"},
{"id":13,"songId":105,"img":"https://robohash.org/voluptatemvoluptatepossimus.png?size=50x50&set=set1","titulo":"elit proin","precio":81,"descripcion":"eu felis fusce posuere felis sed lacus morbi sem mauris laoreet ut rhoncus aliquet","nombre":"Edlin","apellido":"Priddle"},
{"id":20,"songId":106,"img":"https://robohash.org/natusfugiatearum.png?size=50x50&set=set1","titulo":"interdum","precio":47,"descripcion":"potenti nullam porttitor lacus at turpis donec posuere metus vitae ipsum","nombre":"Jacqueline","apellido":"Goldis"},
{"id":47,"songId":107,"img":"https://robohash.org/doloresiustoest.png?size=50x50&set=set1","titulo":"integer a nibh","precio":63,"descripcion":"elementum ligula vehicula consequat morbi a ipsum integer a nibh in quis justo maecenas rhoncus","nombre":"Miof mela","apellido":"Scholz"},
{"id":22,"songId":108,"img":"https://robohash.org/dolornihilconsequatur.png?size=50x50&set=set1","titulo":"ut odio cras","precio":29,"descripcion":"dolor vel est donec odio justo sollicitudin ut suscipit a feugiat et eros vestibulum","nombre":"Todd","apellido":"Bordis"},
{"id":31,"songId":109,"img":"https://robohash.org/quisapientecum.png?size=50x50&set=set1","titulo":"mi pede","precio":97,"descripcion":"suspendisse potenti cras in purus eu magna vulputate luctus cum sociis natoque penatibus et magnis","nombre":"Phip","apellido":"Machen"},
{"id":24,"songId":110,"img":"https://robohash.org/illummagnamiure.png?size=50x50&set=set1","titulo":"faucibus orci luctus","precio":32,"descripcion":"turpis adipiscing lorem vitae mattis nibh ligula nec sem duis aliquam convallis nunc","nombre":"Estevan","apellido":"Parkes"},
{"id":20,"songId":111,"img":"https://robohash.org/vitaereprehenderitesse.png?size=50x50&set=set1","titulo":"turpis nec","precio":25,"descripcion":"sed tristique in tempus sit amet sem fusce consequat nulla nisl nunc","nombre":"Wildon","apellido":"Wharf"},
{"id":10,"songId":112,"img":"https://robohash.org/quodlaudantiumdolores.png?size=50x50&set=set1","titulo":"libero nullam sit","precio":19,"descripcion":"quam turpis adipiscing lorem vitae mattis nibh ligula nec sem duis","nombre":"Sidonnie","apellido":"Haycock"},
{"id":11,"songId":113,"img":"https://robohash.org/quaeratsedomnis.png?size=50x50&set=set1","titulo":"amet erat nulla","precio":62,"descripcion":"consectetuer eget rutrum at lorem integer tincidunt ante vel ipsum praesent blandit lacinia erat","nombre":"Martie","apellido":"Mallam"},
{"id":36,"songId":114,"img":"https://robohash.org/autillumratione.png?size=50x50&set=set1","titulo":"curae duis","precio":48,"descripcion":"nulla nisl nunc nisl duis bibendum felis sed interdum venenatis","nombre":"Harry","apellido":"Littlejohns"},
{"id":37,"songId":115,"img":"https://robohash.org/veritatisassumendacupiditate.png?size=50x50&set=set1","titulo":"sapien in","precio":75,"descripcion":"praesent lectus vestibulum quam sapien varius ut blandit non interdum in","nombre":"Colleen","apellido":"Baldock"},
{"id":36,"songId":116,"img":"https://robohash.org/temporeautiste.png?size=50x50&set=set1","titulo":"mauris lacinia sapien","precio":95,"descripcion":"felis sed interdum venenatis turpis enim blandit mi in porttitor pede justo eu","nombre":"Maurice","apellido":"Petrik"},
{"id":12,"songId":117,"img":"https://robohash.org/consequunturcupiditateut.png?size=50x50&set=set1","titulo":"phasellus sit amet","precio":84,"descripcion":"tempus vivamus in felis eu sapien cursus vestibulum proin eu","nombre":"Cooper","apellido":"Neesham"},
{"id":13,"songId":118,"img":"https://robohash.org/voluptatemeamolestiae.png?size=50x50&set=set1","titulo":"magna","precio":43,"descripcion":"sit amet consectetuer adipiscing elit proin interdum mauris non ligula pellentesque","nombre":"Leda","apellido":"Lismer"},
{"id":7,"songId":119,"img":"https://robohash.org/necessitatibusmollitiaet.png?size=50x50&set=set1","titulo":"tortor","precio":4,"descripcion":"nulla tellus in sagittis dui vel nisl duis ac nibh fusce","nombre":"Enrika","apellido":"Semerad"},
{"id":34,"songId":120,"img":"https://robohash.org/reiciendisetquasi.png?size=50x50&set=set1","titulo":"cras pellentesque volutpat","precio":48,"descripcion":"nulla ac enim in tempor turpis nec euismod scelerisque quam turpis","nombre":"Devon","apellido":"Trevers"},
{"id":16,"songId":121,"img":"https://robohash.org/fugiatsintiure.png?size=50x50&set=set1","titulo":"erat","precio":42,"descripcion":"habitasse platea dictumst etiam faucibus cursus urna ut tellus nulla ut erat id mauris","nombre":"Mohandas","apellido":"Scramage"},
{"id":29,"songId":122,"img":"https://robohash.org/sintametexplicabo.png?size=50x50&set=set1","titulo":"mattis nibh","precio":19,"descripcion":"elementum eu interdum eu tincidunt in leo maecenas pulvinar lobortis est","nombre":"Douglass","apellido":"Goodrick"},
{"id":2,"songId":123,"img":"https://robohash.org/sitestet.png?size=50x50&set=set1","titulo":"fusce","precio":77,"descripcion":"vivamus metus arcu adipiscing molestie hendrerit at vulputate vitae nisl aenean lectus pellentesque eget","nombre":"Daphna","apellido":"Miere"},
{"id":19,"songId":124,"img":"https://robohash.org/odioperferendisab.png?size=50x50&set=set1","titulo":"dui","precio":82,"descripcion":"cum sociis natoque penatibus et magnis dis parturient montes nascetur ridiculus mus vivamus vestibulum sagittis","nombre":"Cristiano","apellido":"Kinkade"},
{"id":25,"songId":125,"img":"https://robohash.org/autvoluptateiusto.png?size=50x50&set=set1","titulo":"ut","precio":69,"descripcion":"faucibus orci luctus et ultrices posuere cubilia curae mauris viverra diam vitae","nombre":"Rosalinde","apellido":"Jocic"},
{"id":30,"songId":126,"img":"https://robohash.org/velquaeratperspiciatis.png?size=50x50&set=set1","titulo":"volutpat dui maecenas","precio":68,"descripcion":"a nibh in quis justo maecenas rhoncus aliquam lacus morbi quis tortor id","nombre":"Drucill","apellido":"Brooks"},
{"id":1,"songId":127,"img":"https://robohash.org/evenietearumin.png?size=50x50&set=set1","titulo":"semper est","precio":99,"descripcion":"posuere cubilia curae donec pharetra magna vestibulum aliquet ultrices erat tortor sollicitudin mi sit amet","nombre":"Kimbell","apellido":"Deverick"},
{"id":26,"songId":128,"img":"https://robohash.org/enimcommodiinventore.png?size=50x50&set=set1","titulo":"potenti","precio":90,"descripcion":"lacus morbi quis tortor id nulla ultrices aliquet maecenas leo odio","nombre":"Anabelle","apellido":"Gregolin"},
{"id":41,"songId":129,"img":"https://robohash.org/molestiasestid.png?size=50x50&set=set1","titulo":"in imperdiet","precio":73,"descripcion":"erat tortor sollicitudin mi sit amet lobortis sapien sapien non mi integer","nombre":"Kelsey","apellido":"Beddon"},
{"id":33,"songId":130,"img":"https://robohash.org/repellatvoluptatumpariatur.png?size=50x50&set=set1","titulo":"pellentesque at","precio":98,"descripcion":"lectus vestibulum quam sapien varius ut blandit non interdum in ante vestibulum ante ipsum primis","nombre":"Sibyl","apellido":"Iacovaccio"},
{"id":49,"songId":131,"img":"https://robohash.org/temporeerrordignissimos.png?size=50x50&set=set1","titulo":"mus etiam vel","precio":80,"descripcion":"penatibus et magnis dis parturient montes nascetur ridiculus mus etiam vel augue vestibulum rutrum","nombre":"Jayson","apellido":"O'Connolly"},
{"id":48,"songId":132,"img":"https://robohash.org/ipsamperspiciatisquam.png?size=50x50&set=set1","titulo":"eros","precio":12,"descripcion":"mauris enim leo rhoncus sed vestibulum sit amet cursus id turpis integer aliquet massa id","nombre":"Terry","apellido":"Sarfas"},
{"id":3,"songId":133,"img":"https://robohash.org/modinonincidunt.png?size=50x50&set=set1","titulo":"odio justo","precio":53,"descripcion":"nascetur ridiculus mus vivamus vestibulum sagittis sapien cum sociis natoque penatibus","nombre":"Madelin","apellido":"Baiss"},
{"id":9,"songId":134,"img":"https://robohash.org/facilisillumillo.png?size=50x50&set=set1","titulo":"sed","precio":57,"descripcion":"fringilla rhoncus mauris enim leo rhoncus sed vestibulum sit amet cursus id turpis integer aliquet","nombre":"Kassi","apellido":"Battleson"},
{"id":27,"songId":135,"img":"https://robohash.org/adquidolorem.png?size=50x50&set=set1","titulo":"mauris non ligula","precio":25,"descripcion":"odio donec vitae nisi nam ultrices libero non mattis pulvinar nulla pede ullamcorper","nombre":"Farand","apellido":"McTrustram"},
{"id":38,"songId":136,"img":"https://robohash.org/saepeeumut.png?size=50x50&set=set1","titulo":"dictumst maecenas","precio":42,"descripcion":"id luctus nec molestie sed justo pellentesque viverra pede ac diam cras pellentesque volutpat dui","nombre":"Artur","apellido":"Jannings"},
{"id":36,"songId":137,"img":"https://robohash.org/etquoquia.png?size=50x50&set=set1","titulo":"vel","precio":44,"descripcion":"ullamcorper augue a suscipit nulla elit ac nulla sed vel enim","nombre":"Althea","apellido":"Winspeare"},
{"id":50,"songId":138,"img":"https://robohash.org/eumblanditiisesse.png?size=50x50&set=set1","titulo":"vulputate luctus","precio":57,"descripcion":"tempus vel pede morbi porttitor lorem id ligula suspendisse ornare consequat lectus in est","nombre":"Illa","apellido":"Klampt"},
{"id":12,"songId":139,"img":"https://robohash.org/etvoluptatemqui.png?size=50x50&set=set1","titulo":"auctor gravida sem","precio":3,"descripcion":"vulputate elementum nullam varius nulla facilisi cras non velit nec nisi vulputate","nombre":"Cassandre","apellido":"Rikkard"},
{"id":9,"songId":140,"img":"https://robohash.org/consequatureaqueadipisci.png?size=50x50&set=set1","titulo":"sed","precio":80,"descripcion":"quis orci eget orci vehicula condimentum curabitur in libero ut massa volutpat convallis","nombre":"Walliw","apellido":"Gerson"},
{"id":28,"songId":141,"img":"https://robohash.org/possimusrecusandaedolor.png?size=50x50&set=set1","titulo":"id nulla ultrices","precio":49,"descripcion":"volutpat sapien arcu sed augue aliquam erat volutpat in congue etiam justo","nombre":"Binnie","apellido":"Mattecot"},
{"id":4,"songId":142,"img":"https://robohash.org/nihilquasdolor.png?size=50x50&set=set1","titulo":"sem mauris","precio":68,"descripcion":"ligula nec sem duis aliquam convallis nunc proin at turpis a pede posuere nonummy","nombre":"Ralina","apellido":"Shakeshaft"},
{"id":32,"songId":143,"img":"https://robohash.org/noneumomnis.png?size=50x50&set=set1","titulo":"lorem","precio":65,"descripcion":"dapibus nulla suscipit ligula in lacus curabitur at ipsum ac","nombre":"Opaline","apellido":"Aldus"},
{"id":49,"songId":144,"img":"https://robohash.org/quiseligendivel.png?size=50x50&set=set1","titulo":"tempor","precio":7,"descripcion":"tellus nulla ut erat id mauris vulputate elementum nullam varius","nombre":"Rourke","apellido":"Newborn"},
{"id":7,"songId":145,"img":"https://robohash.org/etautreiciendis.png?size=50x50&set=set1","titulo":"curae duis faucibus","precio":80,"descripcion":"orci luctus et ultrices posuere cubilia curae duis faucibus accumsan","nombre":"Abraham","apellido":"Bartelli"},
{"id":38,"songId":146,"img":"https://robohash.org/doloribusconsequunturoptio.png?size=50x50&set=set1","titulo":"in sagittis","precio":79,"descripcion":"erat volutpat in congue etiam justo etiam pretium iaculis justo in hac","nombre":"Britte","apellido":"Petrasch"},
{"id":21,"songId":147,"img":"https://robohash.org/nihiletsed.png?size=50x50&set=set1","titulo":"eu","precio":81,"descripcion":"duis consequat dui nec nisi volutpat eleifend donec ut dolor","nombre":"Noby","apellido":"Ridett"},
{"id":30,"songId":148,"img":"https://robohash.org/natusquiconsequatur.png?size=50x50&set=set1","titulo":"ante ipsum","precio":8,"descripcion":"nascetur ridiculus mus etiam vel augue vestibulum rutrum rutrum neque aenean auctor","nombre":"Bell","apellido":"Glaysher"},
{"id":19,"songId":149,"img":"https://robohash.org/laborenondolor.png?size=50x50&set=set1","titulo":"congue elementum","precio":14,"descripcion":"luctus tincidunt nulla mollis molestie lorem quisque ut erat curabitur gravida nisi at","nombre":"Morly","apellido":"Giovanardi"},
{"id":43,"songId":150,"img":"https://robohash.org/dolorumquiaccusantium.png?size=50x50&set=set1","titulo":"pede justo","precio":64,"descripcion":"amet consectetuer adipiscing elit proin risus praesent lectus vestibulum quam sapien varius ut blandit non","nombre":"Sollie","apellido":"Rountree"}]